{"cameraMode":{"drawMode":0,"name":"Shaded","section":"Shading Mode"},"sceneLighting":false,"audioPlay":false,"sceneViewState":{"showFog":true,"showMaterialUpdate":false,"showSkybox":false,"showFlares":true,"showImageEffects":true,"showParticleSystems":true},"in2DMode":false,"pivot":{"x":0.000013999640941619873,"y":0.12000005692243576,"z":-0.36207905411720278},"rotation":{"x":0.0030339707154780628,"y":-0.9960247278213501,"z":0.08086878061294556,"w":0.042078468948602679},"size":0.15743876993656159,"orthographic":false}